popularity/__init__.py
popularity/apps.py
popularity/models.py
popularity/receivers.py
popularity/tasks.py
popularity/utils.py
popularity/views.py
popularity/templatetags/__init__.py
popularity/templatetags/popularity_tags.py
django_popularity_mixin-0.1.8.dist-info/AUTHORS
django_popularity_mixin-0.1.8.dist-info/LICENSE
django_popularity_mixin-0.1.8.dist-info/METADATA
django_popularity_mixin-0.1.8.dist-info/WHEEL
django_popularity_mixin-0.1.8.dist-info/top_level.txt
django_popularity_mixin-0.1.8.dist-info/RECORD
