Metadata-Version: 2.1
Name: django-popularity-mixin
Version: 0.1.8
Summary: Simple integration between django-cacheback and django-hitcount
Home-page: https://github.com/bashu/django-popularity-mixin
Author: Basil Shubin
Author-email: basil.shubin@gmail.com
License: LGPLv3 License
Download-URL: https://github.com/bashu/django-popularity-mixin/zipball/master
Platform: UNKNOWN
Classifier: Development Status :: 5 - Production/Stable
Classifier: Environment :: Web Environment
Classifier: Framework :: Django
Classifier: Intended Audience :: Developers
Classifier: License :: OSI Approved :: GNU Lesser General Public License v3 (LGPLv3)
Classifier: Operating System :: OS Independent
Classifier: Programming Language :: Python
Classifier: Programming Language :: Python :: 2
Classifier: Programming Language :: Python :: 2.7
Classifier: Programming Language :: Python :: 3
Classifier: Programming Language :: Python :: 3.4
Classifier: Topic :: Internet :: WWW/HTTP
Classifier: Topic :: Internet :: WWW/HTTP :: Dynamic Content
Requires: Django (>=1.4.2)
Requires-Dist: django-cacheback
Requires-Dist: django-hitcount (>1.2)
